LICENSE.txt
README.txt
setup.py
misc/__init__.py
misc/ez_setup.py
misc/googlecode_upload.py
misc/release_instructions.txt
pyvol/__init__.py
pyvol.egg-info/PKG-INFO
pyvol.egg-info/SOURCES.txt
pyvol.egg-info/dependency_links.txt
pyvol.egg-info/top_level.txt
pyvol.egg-info/zip-safe
pyvol/est/CovEst.py
pyvol/est/CovUtils.py
pyvol/est/__init__.py
pyvol/experimental/BestEstimator.py
pyvol/experimental/ExampleEstimators.py
pyvol/experimental/__init__.py
pyvol/sims/DataSimulator.py
pyvol/sims/EvaluateBestEstimator.py
pyvol/sims/Evaluator.py
pyvol/sims/MultiClusterSimulator.py
pyvol/sims/SimAPI.py
pyvol/sims/__init__.py
pyvol/sims/__init___flymake.py
pyvol/testing/__init__.py
pyvol/testing/_test_EvalBest.py
pyvol/testing/unitTestsFromSrc.py
pyvol/tseries/ExcelTools.py
pyvol/tseries/Sequence.py
pyvol/tseries/Transforms.py
pyvol/tseries/__init__.py