Metadata-Version: 1.1
Name: pyvol
Version: 1.0
Summary: Volatility estimation in python.
Home-page: http://code.google.com/p/pyvol/
Author: Emin Martinian, Li Lee, Henry Xu
Author-email: emin.martinian@gmail.com
License: MIT
Keywords: volatility,estimation
Platform: UNKNOWN
Provides: pyvol
